add_staves/__init__.py
add_staves/app.py
add_staves/staves/empty-0.pdf
add_staves/staves/empty-1.pdf
add_staves/staves/empty-2.pdf
add_staves/staves/empty-3.pdf
add_staves/staves/empty-4.pdf
add_staves/staves/empty-5.pdf
add_staves/staves/empty-6.pdf
add_staves-0.2.10.dist-info/METADATA
add_staves-0.2.10.dist-info/WHEEL
add_staves-0.2.10.dist-info/entry_points.txt
add_staves-0.2.10.dist-info/RECORD
